OpenweatherPy.py
openweatherpy-0.0.7.dist-info/LICENSE
openweatherpy-0.0.7.dist-info/METADATA
openweatherpy-0.0.7.dist-info/WHEEL
openweatherpy-0.0.7.dist-info/top_level.txt
openweatherpy-0.0.7.dist-info/RECORD
